test/__init__.py
test/config_manager.py
tutils/__init__.py
tutils/classify.py
tutils/functools.py
tutils/initializer.py
tutils/tutils.py
tutils/contrib/__init__.py
tutils/contrib/ddp_demo.py
tutils/contrib/debug_tools.py
tutils/contrib/fourier.py
tutils/contrib/other_package.py
tutils/contrib/pudb_debug.py
tutils/contrib/shutils.py
tutils/contrib/tmp.py
tutils/contrib/proj-template/__init__.py
tutils/contrib/proj-template/code/__init__.py
tutils/contrib/proj-template/code/configs/__init__.py
tutils/contrib/proj-template/code/datasets/__init__.py
tutils/contrib/proj-template/code/networks/__init__.py
tutils/contrib/proj-template/code/scripts/__init__.py
tutils/contrib/proj-template/code/scripts/template.py
tutils/contrib/proj-template/code/test/__init__.py
tutils/contrib/proj-template/code/test/datasets/__init__.py
tutils/contrib/proj-template/code/test/networks/__init__.py
tutils/contrib/proj-template/code/test/utils/__init__.py
tutils/contrib/proj-template/code/tmp/__init__.py
tutils/contrib/proj-template/code/utils/__init__.py
tutils/contrib/proj-template/data/__init__.py
tutils/contrib/proj-template/related_work_1/__init__.py
tutils/contrib/proj-template/related_work_1/work1/__init__.py
tutils/contrib/proj-template/runs/__init__.py
tutils/contrib/test/__init__.py
tutils/contrib/test/test_builtins.py
tutils/contrib/test/test_initializer.py
tutils/contrib/test/test_print.py
tutils/contrib/test/test_pytest.py
tutils/mn/__init__.py
tutils/mn/data/__init__.py
tutils/mn/data/base_dataset.py
tutils/mn/data/base_options.py
tutils/mn/data/data_preprocess.py
tutils/mn/data/augment/__init__.py
tutils/mn/data/augment/augment.py
tutils/mn/data/augment/autoaugment.py
tutils/mn/data/augment/common_2d_aug.py
tutils/mn/data/augment/demo_monai_augment.py
tutils/mn/data/augment/edge_detection.py
tutils/mn/data/augment/gaussian.py
tutils/mn/data/augment/patching.py
tutils/mn/data/tsitk/__init__.py
tutils/mn/data/tsitk/io.py
tutils/mn/data/tsitk/preprocess.py
trans_utils-0.4.3.2.dist-info/LICENSE
trans_utils-0.4.3.2.dist-info/METADATA
trans_utils-0.4.3.2.dist-info/WHEEL
trans_utils-0.4.3.2.dist-info/entry_points.txt
trans_utils-0.4.3.2.dist-info/top_level.txt
trans_utils-0.4.3.2.dist-info/RECORD
