Metadata-Version: 2.1
Name: trans-utils
Version: 0.4.3.2
Summary: UNKNOWN
Home-page: UNKNOWN
Author: Curliq
Author-email: transcendentsiki@gmail.com
License: UNKNOWN
Platform: UNKNOWN
License-File: LICENSE
Requires-Dist: termcolor
Requires-Dist: einops
Requires-Dist: seaborn
Requires-Dist: matplotlib
Requires-Dist: opencv-python
Requires-Dist: pandas
Requires-Dist: pyyaml
Requires-Dist: yamlloader
Requires-Dist: SimpleITK
Requires-Dist: h5py
Requires-Dist: xlwt
Requires-Dist: openpyxl
Requires-Dist: pyradiomics
Requires-Dist: medpy
Requires-Dist: scipy
Requires-Dist: tqdm
Requires-Dist: monai
Requires-Dist: gpustat
Requires-Dist: vscodedebugvisualizer
